[
  {
    "_id": "SWAP",
    "_type": "visualization",
    "_source": {
      "title": "SWAP",
      "visState": "{\"aggs\":[{\"id\":\"1\",\"params\":{\"field\":\"value\"},\"schema\":\"metric\",\"type\":\"max\"},{\"id\":\"2\",\"params\":{\"customInterval\":\"2h\",\"extended_bounds\":{},\"field\":\"@timestamp\",\"interval\":\"s\",\"min_doc_count\":1},\"schema\":\"segment\",\"type\":\"date_histogram\"},{\"id\":\"3\",\"params\":{\"field\":\"type_instance\",\"order\":\"desc\",\"orderBy\":\"1\",\"size\":5},\"schema\":\"group\",\"type\":\"terms\"}],\"listeners\":{},\"params\":{\"addLegend\":true,\"addTimeMarker\":false,\"addTooltip\":true,\"defaultYExtents\":false,\"drawLinesBetweenPoints\":true,\"interpolate\":\"linear\",\"radiusRatio\":9,\"scale\":\"linear\",\"setYExtents\":false,\"shareYAxis\":true,\"showCircles\":true,\"smoothLines\":false,\"times\":[],\"yAxis\":{}},\"type\":\"line\"}",
      "description": "",
      "version": 1,
      "kibanaSavedObjectMeta": {
        "searchSourceJSON": "{\"index\":\"collectd\",\"query\":{\"query_string\":{\"analyze_wildcard\":true,\"query\":\"plugin: swap\"}},\"filter\":[]}"
      }
    }
  },
  {
    "_id": "DF-(MB)",
    "_type": "visualization",
    "_source": {
      "title": "DF (MB)",
      "visState": "{\"type\":\"line\",\"params\":{\"addLegend\":true,\"addTimeMarker\":false,\"addTooltip\":true,\"defaultYExtents\":false,\"drawLinesBetweenPoints\":true,\"interpolate\":\"linear\",\"radiusRatio\":9,\"scale\":\"linear\",\"setYExtents\":false,\"shareYAxis\":true,\"showCircles\":false,\"smoothLines\":false,\"times\":[],\"yAxis\":{}},\"aggs\":[{\"id\":\"1\",\"type\":\"max\",\"schema\":\"metric\",\"params\":{\"field\":\"MB\"}},{\"id\":\"2\",\"type\":\"date_histogram\",\"schema\":\"segment\",\"params\":{\"field\":\"@timestamp\",\"interval\":\"s\",\"customInterval\":\"2h\",\"min_doc_count\":1,\"extended_bounds\":{}}},{\"id\":\"3\",\"type\":\"terms\",\"schema\":\"group\",\"params\":{\"field\":\"type_instance\",\"size\":10,\"order\":\"desc\",\"orderBy\":\"1\"}},{\"id\":\"4\",\"type\":\"terms\",\"schema\":\"split\",\"params\":{\"field\":\"plugin_instance\",\"size\":5,\"order\":\"desc\",\"orderBy\":\"1\",\"row\":true}}],\"listeners\":{}}",
      "description": "",
      "version": 1,
      "kibanaSavedObjectMeta": {
        "searchSourceJSON": "{\"index\":\"collectd\",\"query\":{\"query_string\":{\"analyze_wildcard\":true,\"query\":\"plugin: df\"}},\"filter\":[]}"
      }
    }
  },
  {
    "_id": "Failed-slash-Passed-(-Test-report-)",
    "_type": "visualization",
    "_source": {
      "title": "Failed / Passed ( Test report )",
      "visState": "{\"type\":\"histogram\",\"params\":{\"shareYAxis\":true,\"addTooltip\":true,\"addLegend\":true,\"scale\":\"linear\",\"mode\":\"stacked\",\"times\":[],\"addTimeMarker\":false,\"defaultYExtents\":false,\"setYExtents\":false,\"yAxis\":{}},\"aggs\":[{\"id\":\"1\",\"type\":\"count\",\"schema\":\"metric\",\"params\":{}},{\"id\":\"4\",\"type\":\"date_histogram\",\"schema\":\"segment\",\"params\":{\"field\":\"timestamp\",\"interval\":\"auto\",\"customInterval\":\"2h\",\"min_doc_count\":1,\"extended_bounds\":{}}},{\"id\":\"5\",\"type\":\"terms\",\"schema\":\"split\",\"params\":{\"field\":\"testCaseState\",\"size\":2,\"order\":\"desc\",\"orderBy\":\"1\",\"row\":true}}],\"listeners\":{}}",
      "description": "",
      "version": 1,
      "kibanaSavedObjectMeta": {
        "searchSourceJSON": "{\"index\":\"testreport\",\"query\":{\"query_string\":{\"query\":\"*\",\"analyze_wildcard\":true}},\"filter\":[]}"
      }
    }
  },
  {
    "_id": "Tests-(-Test-report-)",
    "_type": "visualization",
    "_source": {
      "title": "Tests ( Test report )",
      "visState": "{\"type\":\"histogram\",\"params\":{\"shareYAxis\":true,\"addTooltip\":true,\"addLegend\":true,\"scale\":\"linear\",\"mode\":\"stacked\",\"times\":[],\"addTimeMarker\":false,\"defaultYExtents\":false,\"setYExtents\":false,\"yAxis\":{}},\"aggs\":[{\"id\":\"1\",\"type\":\"count\",\"schema\":\"metric\",\"params\":{}},{\"id\":\"2\",\"type\":\"date_histogram\",\"schema\":\"segment\",\"params\":{\"field\":\"timestamp\",\"interval\":\"m\",\"customInterval\":\"2h\",\"min_doc_count\":1,\"extended_bounds\":{}}}],\"listeners\":{}}",
      "description": "",
      "version": 1,
      "kibanaSavedObjectMeta": {
        "searchSourceJSON": "{\"index\":\"testreport\",\"query\":{\"query_string\":{\"query\":\"harness: testEnd\",\"analyze_wildcard\":true}},\"filter\":[]}"
      }
    }
  },
  {
    "_id": "Memory",
    "_type": "visualization",
    "_source": {
      "title": "Memory",
      "visState": "{\"type\":\"pie\",\"params\":{\"shareYAxis\":true,\"addTooltip\":true,\"addLegend\":true,\"isDonut\":false},\"aggs\":[{\"id\":\"1\",\"type\":\"sum\",\"schema\":\"metric\",\"params\":{\"field\":\"value\"}},{\"id\":\"2\",\"type\":\"filters\",\"schema\":\"split\",\"params\":{\"filters\":[{\"input\":{\"query\":{\"query_string\":{\"query\":\"collectd_type: 'memory'\",\"analyze_wildcard\":true}}}}],\"row\":true}},{\"id\":\"3\",\"type\":\"terms\",\"schema\":\"segment\",\"params\":{\"field\":\"type_instance.raw\",\"size\":5,\"order\":\"desc\",\"orderBy\":\"1\"}}],\"listeners\":{}}",
      "description": "",
      "version": 1,
      "kibanaSavedObjectMeta": {
        "searchSourceJSON": "{\"index\":\"logstash-*\",\"query\":{\"query_string\":{\"query\":\"*\",\"analyze_wildcard\":true}},\"filter\":[]}"
      }
    }
  },
  {
    "_id": "Ping",
    "_type": "visualization",
    "_source": {
      "title": "Ping",
      "visState": "{\"type\":\"line\",\"params\":{\"addLegend\":true,\"addTimeMarker\":false,\"addTooltip\":true,\"defaultYExtents\":false,\"drawLinesBetweenPoints\":true,\"interpolate\":\"linear\",\"radiusRatio\":9,\"scale\":\"linear\",\"setYExtents\":false,\"shareYAxis\":true,\"showCircles\":false,\"smoothLines\":false,\"times\":[],\"yAxis\":{}},\"aggs\":[{\"id\":\"1\",\"type\":\"avg\",\"schema\":\"metric\",\"params\":{\"field\":\"value\"}},{\"id\":\"2\",\"type\":\"date_histogram\",\"schema\":\"segment\",\"params\":{\"field\":\"@timestamp\",\"interval\":\"s\",\"customInterval\":\"2h\",\"min_doc_count\":1,\"extended_bounds\":{}}},{\"id\":\"3\",\"type\":\"filters\",\"schema\":\"group\",\"params\":{\"filters\":[{\"input\":{\"query\":{\"query_string\":{\"analyze_wildcard\":true,\"query\":\"collectd_type: ping\"}}}},{\"input\":{\"query\":{\"query_string\":{\"analyze_wildcard\":true,\"query\":\"analyze_wildcard: true\"}}}}]}}],\"listeners\":{}}",
      "description": "",
      "version": 1,
      "kibanaSavedObjectMeta": {
        "searchSourceJSON": "{\"index\":\"collectd\",\"query\":{\"query_string\":{\"analyze_wildcard\":true,\"query\":\"*\"}},\"filter\":[]}"
      }
    }
  },
  {
    "_id": "Interface-(kb)",
    "_type": "visualization",
    "_source": {
      "title": "Interface (kb)",
      "visState": "{\"aggs\":[{\"id\":\"1\",\"params\":{\"field\":\"rxToKb\"},\"schema\":\"metric\",\"type\":\"max\"},{\"id\":\"3\",\"params\":{\"filters\":[{\"input\":{\"query\":{\"query_string\":{\"analyze_wildcard\":true,\"query\":\"plugin: interface\"}}}}]},\"schema\":\"group\",\"type\":\"filters\"},{\"id\":\"4\",\"params\":{\"field\":\"plugin_instance\",\"order\":\"desc\",\"orderBy\":\"1\",\"row\":true,\"size\":5},\"schema\":\"split\",\"type\":\"terms\"},{\"id\":\"6\",\"params\":{\"customInterval\":\"2h\",\"extended_bounds\":{},\"field\":\"@timestamp\",\"interval\":\"auto\",\"min_doc_count\":1},\"schema\":\"segment\",\"type\":\"date_histogram\"},{\"id\":\"7\",\"params\":{\"field\":\"txToKbe\"},\"schema\":\"metric\",\"type\":\"max\"}],\"listeners\":{},\"params\":{\"addLegend\":true,\"addTimeMarker\":false,\"addTooltip\":true,\"defaultYExtents\":false,\"drawLinesBetweenPoints\":true,\"interpolate\":\"linear\",\"radiusRatio\":\"1\",\"scale\":\"linear\",\"setYExtents\":false,\"shareYAxis\":true,\"showCircles\":false,\"smoothLines\":false,\"times\":[],\"yAxis\":{}},\"type\":\"line\"}",
      "description": "",
      "version": 1,
      "kibanaSavedObjectMeta": {
        "searchSourceJSON": "{\"index\":\"collectd\",\"query\":{\"query_string\":{\"analyze_wildcard\":true,\"query\":\"*\"}},\"filter\":[]}"
      }
    }
  },
  {
    "_id": "Test-duration-(-max-slash-min-)-(-Test-report-)",
    "_type": "visualization",
    "_source": {
      "title": "Test duration ( max / min ) ( Test report )",
      "visState": "{\"type\":\"line\",\"params\":{\"shareYAxis\":true,\"addTooltip\":true,\"addLegend\":true,\"showCircles\":false,\"smoothLines\":false,\"interpolate\":\"linear\",\"scale\":\"linear\",\"drawLinesBetweenPoints\":true,\"radiusRatio\":9,\"times\":[],\"addTimeMarker\":false,\"defaultYExtents\":false,\"setYExtents\":false,\"yAxis\":{}},\"aggs\":[{\"id\":\"1\",\"type\":\"max\",\"schema\":\"metric\",\"params\":{\"field\":\"msToS\"}},{\"id\":\"2\",\"type\":\"date_histogram\",\"schema\":\"segment\",\"params\":{\"field\":\"timestamp\",\"interval\":\"auto\",\"customInterval\":\"2h\",\"min_doc_count\":1,\"extended_bounds\":{}}}],\"listeners\":{}}",
      "description": "",
      "version": 1,
      "kibanaSavedObjectMeta": {
        "searchSourceJSON": "{\"index\":\"testreport\",\"query\":{\"query_string\":{\"query\":\"*\",\"analyze_wildcard\":true}},\"filter\":[]}"
      }
    }
  },
  {
    "_id": "Load",
    "_type": "visualization",
    "_source": {
      "title": "Load",
      "visState": "{\"type\":\"line\",\"params\":{\"shareYAxis\":true,\"addTooltip\":true,\"addLegend\":true,\"showCircles\":false,\"smoothLines\":false,\"interpolate\":\"linear\",\"scale\":\"linear\",\"drawLinesBetweenPoints\":true,\"radiusRatio\":9,\"times\":[],\"addTimeMarker\":false,\"defaultYExtents\":false,\"setYExtents\":false,\"yAxis\":{}},\"aggs\":[{\"id\":\"1\",\"type\":\"avg\",\"schema\":\"metric\",\"params\":{\"field\":\"longterm\"}},{\"id\":\"2\",\"type\":\"avg\",\"schema\":\"metric\",\"params\":{\"field\":\"midterm\"}},{\"id\":\"3\",\"type\":\"avg\",\"schema\":\"metric\",\"params\":{\"field\":\"shortterm\"}},{\"id\":\"4\",\"type\":\"date_histogram\",\"schema\":\"segment\",\"params\":{\"field\":\"@timestamp\",\"interval\":\"auto\",\"customInterval\":\"2h\",\"min_doc_count\":1,\"extended_bounds\":{}}}],\"listeners\":{}}",
      "description": "",
      "version": 1,
      "kibanaSavedObjectMeta": {
        "searchSourceJSON": "{\"index\":\"collectd\",\"query\":{\"query_string\":{\"query\":\"plugin: load\",\"analyze_wildcard\":true}},\"filter\":[]}"
      }
    }
  },
  {
    "_id": "CPU",
    "_type": "visualization",
    "_source": {
      "title": "CPU",
      "visState": "{\"type\":\"line\",\"params\":{\"addLegend\":true,\"addTimeMarker\":false,\"addTooltip\":true,\"defaultYExtents\":false,\"drawLinesBetweenPoints\":true,\"interpolate\":\"linear\",\"radiusRatio\":9,\"scale\":\"linear\",\"setYExtents\":false,\"shareYAxis\":true,\"showCircles\":false,\"smoothLines\":false,\"times\":[],\"yAxis\":{}},\"aggs\":[{\"id\":\"1\",\"type\":\"avg\",\"schema\":\"metric\",\"params\":{\"field\":\"cpu_value\"}},{\"id\":\"2\",\"type\":\"date_histogram\",\"schema\":\"segment\",\"params\":{\"field\":\"@timestamp\",\"interval\":\"s\",\"customInterval\":\"2h\",\"min_doc_count\":1,\"extended_bounds\":{}}},{\"id\":\"3\",\"type\":\"terms\",\"schema\":\"group\",\"params\":{\"field\":\"type_instance\",\"size\":10,\"order\":\"desc\",\"orderBy\":\"1\"}},{\"id\":\"4\",\"type\":\"terms\",\"schema\":\"split\",\"params\":{\"field\":\"plugin_instance\",\"size\":5,\"order\":\"desc\",\"orderBy\":\"1\",\"row\":true}}],\"listeners\":{}}",
      "description": "",
      "version": 1,
      "kibanaSavedObjectMeta": {
        "searchSourceJSON": "{\"index\":\"collectd\",\"query\":{\"query_string\":{\"query\":\"plugin: \\\"cpu\\\"\",\"analyze_wildcard\":true}},\"filter\":[]}"
      }
    }
  },
  {
    "_id": "Steps-duration",
    "_type": "visualization",
    "_source": {
      "title": "Steps duration",
      "visState": "{\"aggs\":[{\"id\":\"1\",\"params\":{\"field\":\"duration\"},\"schema\":\"metric\",\"type\":\"max\"},{\"id\":\"2\",\"params\":{\"field\":\"duration\",\"order\":\"desc\",\"orderBy\":\"1\",\"size\":200},\"schema\":\"group\",\"type\":\"terms\"},{\"id\":\"3\",\"params\":{\"field\":\"title\",\"order\":\"desc\",\"orderBy\":\"1\",\"row\":false,\"size\":2},\"schema\":\"split\",\"type\":\"terms\"},{\"id\":\"4\",\"params\":{\"filters\":[{\"input\":{\"query\":{\"query_string\":{\"analyze_wildcard\":true,\"query\":\"harness: testStep\"}}}}]},\"schema\":\"segment\",\"type\":\"filters\"}],\"listeners\":{},\"params\":{\"addLegend\":true,\"addTimeMarker\":false,\"addTooltip\":true,\"defaultYExtents\":false,\"mode\":\"grouped\",\"scale\":\"linear\",\"setYExtents\":false,\"shareYAxis\":true,\"times\":[],\"yAxis\":{}},\"type\":\"histogram\"}",
      "description": "",
      "version": 1,
      "kibanaSavedObjectMeta": {
        "searchSourceJSON": "{\"index\":\"testreport\",\"query\":{\"query_string\":{\"query\":\"*\",\"analyze_wildcard\":true}},\"filter\":[]}"
      }
    }
  },
  {
    "_id": "Dashboards",
    "_type": "visualization",
    "_source": {
      "title": "Dashboards",
      "visState": "{\"type\":\"markdown\",\"params\":{\"markdown\":\"# Dashboards\\n- [Test results](/#/dashboard/Test-report)\\n- [Test case](/#/dashboard/Test-case)\\n- [Server load](/#/dashboard/Load)\"},\"aggs\":[],\"listeners\":{}}",
      "description": "",
      "version": 1,
      "kibanaSavedObjectMeta": {
        "searchSourceJSON": "{\"query\":{\"query_string\":{\"analyze_wildcard\":true,\"query\":\"*\"}},\"filter\":[]}"
      }
    }
  },
  {
    "_id": "Tests-passed",
    "_type": "visualization",
    "_source": {
      "title": "Tests passed",
      "visState": "{\"type\":\"metric\",\"params\":{\"fontSize\":\"25\"},\"aggs\":[{\"id\":\"1\",\"type\":\"count\",\"schema\":\"metric\",\"params\":{}}],\"listeners\":{}}",
      "description": "",
      "version": 1,
      "kibanaSavedObjectMeta": {
        "searchSourceJSON": "{\"index\":\"testreport\",\"query\":{\"query_string\":{\"query\":\"harness: testEnd AND testCaseState: passed\",\"analyze_wildcard\":true}},\"filter\":[]}"
      }
    }
  },
  {
    "_id": "Tests-failed",
    "_type": "visualization",
    "_source": {
      "title": "Tests failed",
      "visState": "{\"type\":\"metric\",\"params\":{\"fontSize\":\"25\"},\"aggs\":[{\"id\":\"1\",\"type\":\"count\",\"schema\":\"metric\",\"params\":{}}],\"listeners\":{}}",
      "description": "",
      "version": 1,
      "kibanaSavedObjectMeta": {
        "searchSourceJSON": "{\"index\":\"testreport\",\"query\":{\"query_string\":{\"query\":\"harness: testEnd AND testCaseState: failed\",\"analyze_wildcard\":true}},\"filter\":[]}"
      }
    }
  },
  {
    "_id": "Tests",
    "_type": "visualization",
    "_source": {
      "title": "Tests",
      "visState": "{\"type\":\"metric\",\"params\":{\"fontSize\":\"25\"},\"aggs\":[{\"id\":\"1\",\"type\":\"count\",\"schema\":\"metric\",\"params\":{}}],\"listeners\":{}}",
      "description": "",
      "version": 1,
      "kibanaSavedObjectMeta": {
        "searchSourceJSON": "{\"index\":\"testreport\",\"query\":{\"query_string\":{\"analyze_wildcard\":true,\"query\":\"harness: testEnd\"}},\"filter\":[]}"
      }
    }
  },
  {
    "_id": "Top-failed",
    "_type": "visualization",
    "_source": {
      "title": "Top failed",
      "visState": "{\"type\":\"table\",\"params\":{\"perPage\":null,\"showMeticsAtAllLevels\":true,\"showPartialRows\":false},\"aggs\":[{\"id\":\"1\",\"type\":\"count\",\"schema\":\"metric\",\"params\":{}},{\"id\":\"2\",\"type\":\"terms\",\"schema\":\"bucket\",\"params\":{\"field\":\"err\",\"size\":300,\"order\":\"desc\",\"orderBy\":\"1\"}}],\"listeners\":{}}",
      "description": "",
      "version": 1,
      "kibanaSavedObjectMeta": {
        "searchSourceJSON": "{\"index\":\"testreport\",\"query\":{\"query_string\":{\"analyze_wildcard\":true,\"query\":\"*\"}},\"filter\":[]}"
      }
    }
  },
  {
    "_id": "RAM-(MB)2",
    "_type": "visualization",
    "_source": {
      "title": "RAM (MB)",
      "visState": "{\n  \"type\": \"line\",\n  \"params\": {\n    \"addLegend\": true,\n    \"addTimeMarker\": true,\n    \"addTooltip\": true,\n    \"defaultYExtents\": false,\n    \"drawLinesBetweenPoints\": true,\n    \"interpolate\": \"linear\",\n    \"radiusRatio\": 9,\n    \"scale\": \"linear\",\n    \"setYExtents\": false,\n    \"shareYAxis\": true,\n    \"showCircles\": false,\n    \"smoothLines\": false,\n    \"times\": [],\n    \"yAxis\": {}\n  },\n  \"aggs\": [\n    {\n      \"id\": \"1\",\n      \"type\": \"max\",\n      \"schema\": \"metric\",\n      \"params\": {\n        \"field\": \"MB\"\n      }\n    },\n    {\n      \"id\": \"2\",\n      \"type\": \"date_histogram\",\n      \"schema\": \"segment\",\n      \"params\": {\n        \"field\": \"@timestamp\",\n        \"interval\": \"s\",\n        \"customInterval\": \"2h\",\n        \"min_doc_count\": 1,\n        \"extended_bounds\": {}\n      }\n    },\n    {\n      \"id\": \"3\",\n      \"type\": \"terms\",\n      \"schema\": \"group\",\n      \"params\": {\n        \"field\": \"type_instance\",\n        \"size\": 5,\n        \"order\": \"desc\",\n        \"orderBy\": \"1\"\n      }\n    }\n  ],\n  \"listeners\": {}\n}",
      "description": "",
      "version": 1,
      "kibanaSavedObjectMeta": {
        "searchSourceJSON": "{\n  \"index\": \"collectd\",\n  \"query\": {\n    \"query_string\": {\n      \"analyze_wildcard\": true,\n      \"query\": \"plugin: memory\"\n    }\n  },\n  \"filter\": []\n}"
      }
    }
  }
]